copyright_code_extractor/__init__.py
copyright_code_extractor/__main__.py
copyright_code_extractor/cli.py
copyright_code_extractor/config.py
copyright_code_extractor/extractor.py
copyright_code_extractor-0.1.0.dist-info/METADATA
copyright_code_extractor-0.1.0.dist-info/WHEEL
copyright_code_extractor-0.1.0.dist-info/entry_points.txt
copyright_code_extractor-0.1.0.dist-info/licenses/LICENSE
copyright_code_extractor-0.1.0.dist-info/RECORD
