Metadata-Version: 2.4
Name: copyright-code-extractor
Version: 0.1.0
Summary: A tool to extract source code for China Software Copyright application.
Project-URL: Repository, https://github.com/kirklin/copyright-code-extractor
Author-email: Kirk Lin <linkirk@163.com>
License: GNU General Public License v3.0
License-File: LICENSE
Requires-Python: >=3.8
Requires-Dist: pydantic<3.0.0,>=2.5.0
Requires-Dist: python-docx<2.0.0,>=1.1.0
Requires-Dist: rich<14.0.0,>=13.0.0
Requires-Dist: typer<1.0.0,>=0.9.0
